xjm_device_tasks/__init__.py
xjm_device_tasks/adb.py
xjm_device_tasks/backend.py
xjm_device_tasks/client.py
xjm_device_tasks/logger.py
xjm_device_tasks/sys_redirect.py
xjm_device_tasks/task.py
xjm_device_tasks/task_comm.py
xjm_device_tasks/task_douyin_last_work_count.py
xjm_device_tasks/task_douyin_publish.py
xjm_device_tasks/task_douyin_sec_uid.py
xjm_device_tasks/task_douyin_update_signature.py
xjm_device_tasks/task_douyin_user_id.py
xjm_device_tasks/task_error.py
xjm_device_tasks/task_file_upload.py
xjm_device_tasks/task_helper.py
xjm_device_tasks/task_idm.py
xjm_device_tasks/task_unlock_phone.py
xjm_device_tasks/task_wechat_add_friend.py
xjm_device_tasks/task_wechat_info.py
xjm_device_tasks/task_xhs_publish.py
xjm_device_tasks/test_client.py
xjm_device_tasks/test_douyin_last_work_count.py
xjm_device_tasks/test_douyin_sec_uid.py
xjm_device_tasks/test_douyin_update_signature.py
xjm_device_tasks/test_douyin_user_id.py
xjm_device_tasks/test_idm_download.py
xjm_device_tasks/test_local_file_upload_task.py
xjm_device_tasks/test_remote_file_upload_task.py
xjm_device_tasks/test_task_comm.py
xjm_device_tasks/test_task_douyin.py
xjm_device_tasks/test_task_wechat_add_friend.py
xjm_device_tasks/test_xhs_publish.py
xjm_device_tasks/util.py
xjm_device_tasks-0.0.9.dist-info/METADATA
xjm_device_tasks-0.0.9.dist-info/WHEEL
xjm_device_tasks-0.0.9.dist-info/top_level.txt
xjm_device_tasks-0.0.9.dist-info/RECORD
