Metadata-Version: 2.1
Name: xjm_device_tasks
Version: 0.0.9
Summary: Android device management and automation tasks
Author: 23233
Author-email: 
Classifier: Programming Language :: Python :: 3
Classifier: License :: OSI Approved :: MIT License
Classifier: Operating System :: OS Independent
Requires-Python: >=3.10
Requires-Dist: pydantic ~=2.7.3
Requires-Dist: requests ~=2.31.0
Requires-Dist: urllib3 ~=2.2.1
Requires-Dist: uiautomator2 ~=3.2.6
Requires-Dist: adbutils ~=2.7.2
Requires-Dist: loguru ~=0.7.2
Requires-Dist: beautifulsoup4 ~=4.12.3
Requires-Dist: retry ~=0.9.2
